SafeRun/__init__.py
SafeRun/__main__.py
SafeRun/saferun.py
SafeRun-1.0.2.dist-info/LICENSE
SafeRun-1.0.2.dist-info/METADATA
SafeRun-1.0.2.dist-info/WHEEL
SafeRun-1.0.2.dist-info/top_level.txt
SafeRun-1.0.2.dist-info/RECORD
