Metadata-Version: 2.1
Name: SafeRun
Version: 1.0.2
Summary: A highly secure sandbox for executing Python code in an isolated environment.
Author: Mohammad Taha Gorji
Author-email: MohammadTahaGorjiProfile@gmail.com
Classifier: Programming Language :: Python :: 3
Classifier: License :: OSI Approved :: MIT License
Classifier: Operating System :: OS Independent
Requires-Python: >=3.6
License-File: LICENSE
